sensirion_shdlc_svm41/__init__.py
sensirion_shdlc_svm41/device.py
sensirion_shdlc_svm41/device_errors.py
sensirion_shdlc_svm41/firmware_image.py
sensirion_shdlc_svm41/response_types.py
sensirion_shdlc_svm41/version.py
sensirion_shdlc_svm41/commands/__init__.py
sensirion_shdlc_svm41/commands/algorithm_parameters.py
sensirion_shdlc_svm41/commands/algorithm_states.py
sensirion_shdlc_svm41/commands/device_information.py
sensirion_shdlc_svm41/commands/device_reset.py
sensirion_shdlc_svm41/commands/firmware_update.py
sensirion_shdlc_svm41/commands/get_system_up_time.py
sensirion_shdlc_svm41/commands/get_version.py
sensirion_shdlc_svm41/commands/read_measured_values.py
sensirion_shdlc_svm41/commands/start_measurement.py
sensirion_shdlc_svm41/commands/stop_measurement.py
sensirion_shdlc_svm41-0.1.0.dist-info/LICENSE
sensirion_shdlc_svm41-0.1.0.dist-info/METADATA
sensirion_shdlc_svm41-0.1.0.dist-info/WHEEL
sensirion_shdlc_svm41-0.1.0.dist-info/top_level.txt
sensirion_shdlc_svm41-0.1.0.dist-info/RECORD
