Metadata-Version: 2.1
Name: sensirion-shdlc-svm41
Version: 0.1.0
Summary: Driver For Communicating With Sensirion SVM41 Evaluation Kit
Home-page: https://github.com/sensirion/python-shdlc-svm41
Author: Philippe Largier
Author-email: info@sensirion.com
License: BSD
Keywords: sensirion shdlc driver svm41
Platform: UNKNOWN
Classifier: Intended Audience :: Developers
Classifier: License :: OSI Approved :: BSD License
Classifier: Programming Language :: Python :: 2.7
Classifier: Programming Language :: Python :: 3.5
Classifier: Programming Language :: Python :: 3.6
Classifier: Programming Language :: Python :: 3.7
Classifier: Programming Language :: Python :: 3.8
Classifier: Topic :: System :: Hardware :: Hardware Drivers
Requires-Python: >=2.7, !=3.0.*, !=3.1.*, !=3.2.*, !=3.3.*, !=3.4.*, <4
Requires-Dist: sensirion-shdlc-driver[fwupdate] (~=0.1.5)
Requires-Dist: enum34 ; python_version < "3.4"
Provides-Extra: test
Requires-Dist: flake8 (~=3.9.2) ; extra == 'test'
Requires-Dist: mock (~=3.0.0) ; extra == 'test'
Requires-Dist: pytest (~=4.6.11) ; extra == 'test'
Requires-Dist: pytest-cov (~=2.6.0) ; extra == 'test'
